<?xml version="1.0" encoding="utf-8" standalone="no"?>
<declaration xmlns="http://xmlexporter.service.taxonline.egov.be" xmlns:xsi="http://www.w3.org/2001/XMLSchema-instance">
  <part1>
    <c1002>checked</c1002>
    <c1030>3</c1030>
    <c1106>1737.00</c1106>
    <c2106>2733.00</c2106>
    <c1108>91.61</c1108>
    <c2108>195.69</c2108>
    <c2250>
      <valeur>41472.41</valeur>
    </c2250>
    <c2251>
      <valeur>4359.38</valeur>
    </c2251>
    <c2260>3458.14</c2260>
    <c2286>
      <valeur>18430.75</valeur>
    </c2286>
    <c2287>243.76</c2287>
    <c1117>32712.32</c1117>
    <c1118>12450.58</c1118>
    <c1119>3039.26</c1119>
    <c1143>395.93</c1143>
    <c1146>344.50</c1146>
    <c2146>4171.67</c2146>
    <c1355>1219.64</c1355>
    <c1358>1029.61</c1358>
    <c2358>2989.79</c2358>
    <c3364>1710.00</c3364>
    <c4364>1710.00</c4364>
    <c1384>2629.17</c1384>
    <c2361>990.00</c2361>
    <c1075>checked</c1075>
    <tituCptEtrg>
      <compte>
        <titulaire>De Stecker Wouter</titulaire>
        <pays>LU</pays>
        <nationalBank>checked</nationalBank>
      </compte>
    </tituCptEtrg>
  </part1>
  <part2>
    <c2200>1150.00</c2200>
    <c2201>230.00</c2201>
    <c1400>
      <valeur>35500.00</valeur>
    </c1400>
    <c1405>8154.16</c1405>
    <c2405>1196.29</c2405>
    <c2400>
      <valeur>0.00</valeur>
      <valeur>0.00</valeur>
    </c2400>
    <c2407>
      <valeur>0.00</valeur>
      <valeur>1096.29</valeur>
    </c2407>
    <c1407>
      <valeur>0.00</valeur>
    </c1407>
    <c2408>100.00</c2408>
  </part2>
</declaration>
