<?xml version="1.0" encoding="utf-8" standalone="no"?>
<declaration xmlns="http://xmlexporter.service.taxonline.egov.be" xmlns:xsi="http://www.w3.org/2001/XMLSchema-instance">
  <part1>
    <c1002>checked</c1002>
    <c1030>1</c1030>
    <c1117>21600.00</c1117>
    <c2117>14400.00</c2117>
    <c1118>9672.50</c1118>
    <c2118>7200.00</c2118>
    <c1119>1789.13</c1119>
    <c2119>1080.00</c2119>
    <c4364>90.00</c4364>
    <c1384>520.75</c1384>
    <c1361>990.00</c1361>
    <c2361>990.00</c2361>
  </part1>
  <part2>
    <c1400>
      <valeur>47755.71</valeur>
    </c1400>
    <c2400>
      <valeur>63937.98</valeur>
    </c2400>
    <c1405>8210.31</c1405>
    <c2405>15937.98</c2405>
    <c1407>
      <valeur>14820.00</valeur>
    </c1407>
    <c2407>
      <valeur>14546.88</valeur>
    </c2407>
  </part2>
</declaration>
